exoscale_dns/__init__.py
exoscale_dns/exoscale_dns.py
exoscale_dns-0.1.2.dist-info/METADATA
exoscale_dns-0.1.2.dist-info/RECORD
exoscale_dns-0.1.2.dist-info/WHEEL
exoscale_dns-0.1.2.dist-info/top_level.txt
