Metadata-Version: 2.1
Name: exoscale-dns
Version: 0.1.2
Summary: Python API for Exoscale's DNS offering
Home-page: https://github.com/digitalmensch/exoscale_dns
Author: Digitalmensch
Author-email: contact@digitalmensch.ch
License: MIT license
Keywords: exoscale_dns
Platform: UNKNOWN
Classifier: Development Status :: 2 - Pre-Alpha
Classifier: Intended Audience :: Developers
Classifier: License :: OSI Approved :: MIT License
Classifier: Natural Language :: English
Classifier: Programming Language :: Python :: 2
Classifier: Programming Language :: Python :: 2.7
Classifier: Programming Language :: Python :: 3
Classifier: Programming Language :: Python :: 3.4
Classifier: Programming Language :: Python :: 3.5
Classifier: Programming Language :: Python :: 3.6
Requires-Dist: attrs
Requires-Dist: requests
